pp_me/__init__.py
pp_me/main.py
pp_me/version.py
pp_me-0.1.3.dist-info/LICENSE
pp_me-0.1.3.dist-info/METADATA
pp_me-0.1.3.dist-info/WHEEL
pp_me-0.1.3.dist-info/entry_points.txt
pp_me-0.1.3.dist-info/top_level.txt
pp_me-0.1.3.dist-info/RECORD
