Metadata-Version: 2.1
Name: pp-me
Version: 0.1.3
Summary: Pretty Print Me!
Home-page: https://nicholassynovic.github.io
Author: Nicholas M. Synovic
Author-email: nicholas.synovic@gmail.com
License: BSD
Project-URL: Bug Tracker, https://github.com/NicholasSynovic/pp-me/issues
Project-URL: GitHub Repository, https://github.com/NicholasSynovic/pp-me
Keywords: pretty,terminal,json
Platform: UNKNOWN
Classifier: Development Status :: 4 - Beta
Classifier: Intended Audience :: Developers
Classifier: License :: OSI Approved :: BSD License
Classifier: Programming Language :: Python
Classifier: Programming Language :: Python :: 3
Classifier: Programming Language :: Python :: 3.9
Classifier: Programming Language :: Python :: 3 :: Only
Classifier: Operating System :: Microsoft :: Windows
Classifier: Operating System :: POSIX
Classifier: Operating System :: Unix
Classifier: Operating System :: MacOS
Requires-Python: >=3.9
License-File: LICENSE
